Metadata-Version: 1.0
Name: aText
Version: 0.8
Summary: Analysis of Text (aText)
Home-page: http://github.com/sjskdas/aText
Author: Subrata Das
Author-email: sdas@machineanalytics.com
License: Machine Analytics
Platform: UNKNOWN
